LePotatoPi/__init__.py
LePotatoPi/GPIO/BoardPinSettings.py
LePotatoPi/GPIO/GPIO.py
LePotatoPi/GPIO/PulseWidthManagement.py
LePotatoPi/GPIO/__init__.py
LePotatoPi/GPIO/consts.py
test/__init__.py
test/blinky.py
LePotatoPi.GPIO-0.0.4.dist-info/LICENSE
LePotatoPi.GPIO-0.0.4.dist-info/METADATA
LePotatoPi.GPIO-0.0.4.dist-info/WHEEL
LePotatoPi.GPIO-0.0.4.dist-info/top_level.txt
LePotatoPi.GPIO-0.0.4.dist-info/RECORD
